Workbook

Sheet Cover
A1: EMAAR PROPERTIES — DCF VALUATION MODEL
A3: Prepared by: Nathan D'Costa
A4: Finance Graduate — Curtin University Dubai
A5: CFA Level 1 Candidate (August 2026)
A6: LinkedIn: linkedin.com/in/nathan-dcosta-502b68251
A7: Date: June 2026
A8: Data Source: Emaar Properties Annual Reports 2022–2024
A9: Methodology: DCF Valuation (FCFF Approach), 5-Year Projection

Sheet 1. Assumptions
A1: EMAAR PROPERTIES — DCF VALUATION MODEL
A2: All figures in AED Millions unless stated
A4: REVENUE GROWTH ASSUMPTIONS | C4: Rate
A5: FY2025E Revenue Growth Rate | C5: 0.1
A6: FY2026E Revenue Growth Rate | C6: 0.09
A7: FY2027E Revenue Growth Rate | C7: 0.08
A8: FY2028E Revenue Growth Rate | C8: 0.07
A9: FY2029E Revenue Growth Rate | C9: 0.06
A10: Terminal Growth Rate (g) | C10: 0.03
A12: MARGIN & PROFITABILITY ASSUMPTIONS | C12: Rate
A13: EBITDA Margin | C13: 0.38
A14: Depreciation & Amortisation (% Revenue) | C14: 0.02
A15: Effective Tax Rate | C15: 0.09
A16: Capex (% Revenue) | C16: 0.02
A17: Change in Working Capital (% Revenue) | C17: 0.02
A19: WACC ASSUMPTIONS | C19: Rate
A20: Risk-Free Rate (UAE 10Y Bond) | C20: 0.045
A21: Equity Risk Premium | C21: 0.055
A22: Beta (Emaar vs ADX) | C22: 0.9
A23: Cost of Equity [=Rf + β × ERP] | C23: =C20+C22*C21 -> 0.0945
A24: Cost of Debt (pre-tax) | C24: 0.05
A25: Tax Rate (for after-tax debt cost) | C25: 0.09
A26: Weight of Equity | C26: 0.7
A27: Weight of Debt | C27: 0.3
A28: WACC [=We×Ke + Wd×Kd×(1-t)] | C28: =C26*C23+C27*C24*(1-C25) -> 0.0798
A30: VALUATION CROSS-CHECK
A31: Shares Outstanding (Millions) | C31: 7340
A32: Net Debt / (Net Cash) — AED Mn | C32: -40370

Sheet 2. Historical Financials
A1: EMAAR PROPERTIES — HISTORICAL FINANCIALS (AED Millions)
A3: Income Statement | B3: FY2022A | C3: FY2023A | D3: FY2024A
A4: Revenue | B4: 24926 | C4: 26750 | D4: 35505
A5: Cost of Revenue | B5: 12338 | C5: 9884 | D5: 15124
A6: Gross Profit | B6: =B4-B5 -> 12588 | C6: =C4-C5 -> 16866 | D6: =D4-D5 -> 20381
A7: Operating Expenses (SG&A) | B7: 3522 | C7: 2786 | D7: 3232
A8: EBITDA | B8: =B6-B7 -> 9066 | C8: =C6-C7 -> 14080 | D8: =D6-D7 -> 17149
A9: Depreciation & Amortisation | B9: 1269 | C9: 1397 | D9: 1427
A10: EBIT (Operating Profit) | B10: =B8-B9 -> 7797 | C10: =C8-C9 -> 12683 | D10: =D8-D9 -> 15722
A11: Interest Expense | B11: 981 | C11: 1039 | D11: 941
A12: Profit Before Tax | B12: =B10-B11 -> 6816 | C12: =C10-C11 -> 11644 | D12: =D10-D11 -> 14781
A13: Tax Expense | B13: 338 | C13: 232 | D13: 1451
A14: Net Profit (Attributable) | B14: =B12-B13 -> 6478 | C14: =C12-C13 -> 11412 | D14: =D12-D13 -> 13330
A16: CASH FLOW STATEMENT (KEY ITEMS)
A17: Net Profit | B17: =B14 -> 6478 | C17: =C14 -> 11412 | D17: =D14 -> 13330
A18: Add: Depreciation & Amortisation | B18: =B9 -> 1269 | C18: =C9 -> 1397 | D18: =D9 -> 1427
A19: Changes in Working Capital | B19: 8229 | C19: 2662 | D19: 5394
A20: Cash Flow from Operations | B20: =B17+B18+B19 -> 15976 | C20: =C17+C18+C19 -> 15471 | D20: =D17+D18+D19 -> 20151
A21: Capital Expenditure (Capex) | B21: 960 | C21: 579 | D21: 534
A22: Free Cash Flow to Firm (FCFF) | B22: =B20-B21 -> 15016 | C22: =C20-C21 -> 14892 | D22: =D20-D21 -> 19617
A24: KEY RATIOS (AUTO-CALCULATED)
A25: Revenue Growth YoY | B25: n/a | C25: =IF(B4=0,"-",(C4-B4)/B4) -> 0.073176603 | D25: =IF(C4=0,"-",(D4-C4)/C4) -> 0.32728972
A26: Gross Margin | B26: =IF(B4=0,"-",B6/B4) -> 0.50501484 | C26: =IF(C4=0,"-",C6/C4) -> 0.63050467 | D26: =IF(D4=0,"-",D6/D4) -> 0.57403183
A27: EBITDA Margin | B27: =IF(B4=0,"-",B8/B4) -> 0.3637166 | C27: =IF(C4=0,"-",C8/C4) -> 0.52635514 | D27: =IF(D4=0,"-",D8/D4) -> 0.48300239
A28: Net Profit Margin | B28: =IF(B4=0,"-",B14/B4) -> 0.25988927 | C28: =IF(C4=0,"-",C14/C4) -> 0.42661682 | D28: =IF(D4=0,"-",D14/D4) -> 0.37544008
A30: 📌 SOURCE: Emaar Annual Reports (emaar.com/investor-relations). Use figures in AED Millions. Source: Emaar Properties Annual Reports 2022, 2023, 2024.

Sheet 3. Projections
A1: EMAAR PROPERTIES — 5-YEAR FINANCIAL PROJECTIONS (AED Millions)
A3: Projections | B3: FY2024A (Base) | C3: FY2025E | D3: FY2026E | E3: FY2027E | F3: FY2028E | G3: FY2029E
A4: Revenue | B4: ='2. Historical Financials'!D4 -> 35505 | C4: =B4*(1+'1. Assumptions'!C5) -> 39055.5 | D4: =C4*(1+'1. Assumptions'!C6) -> 42570.495 | E4: =D4*(1+'1. Assumptions'!C7) -> 45976.135 | F4: =E4*(1+'1. Assumptions'!C8) -> 49194.464 | G4: =F4*(1+'1. Assumptions'!C9) -> 52146.132
A5: EBITDA | B5: ='2. Historical Financials'!D8 -> 17149 | C5: =C4*'1. Assumptions'!C13 -> 14841.09 | D5: =D4*'1. Assumptions'!C13 -> 16176.788 | E5: =E4*'1. Assumptions'!C13 -> 17470.931 | F5: =F4*'1. Assumptions'!C13 -> 18693.896 | G5: =G4*'1. Assumptions'!C13 -> 19815.53
A6: EBITDA Margin | B6: ='2. Historical Financials'!D27 -> 0.48300239 | C6: =IF(C4=0,0,C5/C4) -> 0.38 | D6: =IF(D4=0,0,D5/D4) -> 0.38 | E6: =IF(E4=0,0,E5/E4) -> 0.38 | F6: =IF(F4=0,0,F5/F4) -> 0.38 | G6: =IF(G4=0,0,G5/G4) -> 0.38
A7: Depreciation & Amortisation | B7: ='2. Historical Financials'!D9 -> 1427 | C7: =C4*'1. Assumptions'!C14 -> 781.11 | D7: =D4*'1. Assumptions'!C14 -> 851.4099 | E7: =E4*'1. Assumptions'!C14 -> 919.52269 | F7: =F4*'1. Assumptions'!C14 -> 983.88928 | G7: =G4*'1. Assumptions'!C14 -> 1042.9226
A8: EBIT | B8: ='2. Historical Financials'!D10 -> 15722 | C8: =C5-C7 -> 14059.98 | D8: =D5-D7 -> 15325.378 | E8: =E5-E7 -> 16551.408 | F8: =F5-F7 -> 17710.007 | G8: =G5-G7 -> 18772.607
A9: Tax Expense | C9: =C8*'1. Assumptions'!C15 -> 1265.3982 | D9: =D8*'1. Assumptions'!C15 -> 1379.284 | E9: =E8*'1. Assumptions'!C15 -> 1489.6268 | F9: =F8*'1. Assumptions'!C15 -> 1593.9006 | G9: =G8*'1. Assumptions'!C15 -> 1689.5347
A10: NOPAT (Net Operating Profit After Tax) | C10: =C8-C9 -> 12794.582 | D10: =D8-D9 -> 13946.094 | E10: =E8-E9 -> 15061.782 | F10: =F8-F9 -> 16116.106 | G10: =G8-G9 -> 17083.073
A11: Add: D&A | C11: =C7 -> 781.11 | D11: =D7 -> 851.4099 | E11: =E7 -> 919.52269 | F11: =F7 -> 983.88928 | G11: =G7 -> 1042.9226
A12: Less: Capex | C12: =C4*'1. Assumptions'!C16 -> 781.11 | D12: =D4*'1. Assumptions'!C16 -> 851.4099 | E12: =E4*'1. Assumptions'!C16 -> 919.52269 | F12: =F4*'1. Assumptions'!C16 -> 983.88928 | G12: =G4*'1. Assumptions'!C16 -> 1042.9226
A13: Less: Change in Working Capital | C13: =C4*'1. Assumptions'!C17 -> 781.11 | D13: =D4*'1. Assumptions'!C17 -> 851.4099 | E13: =E4*'1. Assumptions'!C17 -> 919.52269 | F13: =F4*'1. Assumptions'!C17 -> 983.88928 | G13: =G4*'1. Assumptions'!C17 -> 1042.9226
A14: Free Cash Flow to Firm (FCFF) | C14: =C10+C11-C12-C13 -> 12013.472 | D14: =D10+D11-D12-D13 -> 13094.684 | E14: =E10+E11-E12-E13 -> 14142.259 | F14: =F10+F11-F12-F13 -> 15132.217 | G14: =G10+G11-G12-G13 -> 16040.15

Sheet 4. DCF Valuation
A1: EMAAR PROPERTIES — DCF VALUATION (AED Millions)
A3: WACC (from Assumptions) | B3: ='1. Assumptions'!C28 -> 0.0798
A4: Terminal Growth Rate (g) | B4: ='1. Assumptions'!C10 -> 0.03
A6: STEP 1: FREE CASH FLOWS & DISCOUNT FACTORS | C6: FY2025E | D6: FY2026E | E6: FY2027E | F6: FY2028E | G6: FY2029E
A7: Free Cash Flow to Firm (FCFF) | C7: ='3. Projections'!C14 -> 12013.472 | D7: ='3. Projections'!D14 -> 13094.684 | E7: ='3. Projections'!E14 -> 14142.259 | F7: ='3. Projections'!F14 -> 15132.217 | G7: ='3. Projections'!G14 -> 16040.15
A8: Discount Period | C8: 1 | D8: 2 | E8: 3 | F8: 4 | G8: 5
A9: Discount Factor [1/(1+WACC)^n] | C9: =1/(1+$B$3)^C8 -> 0.92609743 | D9: =1/(1+$B$3)^D8 -> 0.85765644 | E9: =1/(1+$B$3)^E8 -> 0.79427342 | F9: =1/(1+$B$3)^F8 -> 0.73557457 | G9: =1/(1+$B$3)^G8 -> 0.68121372
A10: Present Value of FCFF | C10: =C7*C9 -> 11125.645 | D10: =D7*D9 -> 11230.74 | E10: =E7*E9 -> 11232.82 | F10: =F7*F9 -> 11130.874 | G10: =G7*G9 -> 10926.77
A12: STEP 2: TERMINAL VALUE
A13: Terminal Year FCFF (FY2029E) | B13: ='3. Projections'!G14 -> 16040.15
A14: Terminal Value [FCFF × (1+g) / (WACC - g)] | B14: =B13*(1+B4)/(B3-B4) -> 331754.11
A15: PV of Terminal Value | B15: =B14/(1+B3)^5 -> 225995.45
A17: STEP 3: ENTERPRISE & EQUITY VALUE
A18: Sum of PV of FCFFs (FY2025-2029) | B18: =SUM(C10:G10) -> 55646.851
A19: PV of Terminal Value | B19: =B15 -> 225995.45
A20: Enterprise Value (EV) | B20: =B18+B19 -> 281642.3
A21: Less: Net Debt | B21: ='1. Assumptions'!C32 -> -40370
A22: Equity Value | B22: =B20-B21 -> 322012.3
A23: Shares Outstanding (Millions) | B23: ='1. Assumptions'!C31 -> 7340
A24: Implied Share Price (AED) | B24: =B22/B23 -> 43.870886
A25: Current Market Price (AED) — fill in manually | B25: 11.06 | C25: on 10/06/2026
A26: Upside / (Downside) | B26: =IF(B25=0,"-",(B24-B25)/B25) -> 2.9666262

Sheet 5. Sensitivity Analysis
A1: SENSITIVITY ANALYSIS — IMPLIED SHARE PRICE (AED)
A3: WACC \ Terminal Growth | B3: 0.02 | C3: 0.025 | D3: 0.03 | E3: 0.035 | F3: 0.04
A4: 0.08 | B4: =IF((0.08-0.02)<=0,"N/A",('3. Projections'!C14/(1+0.08)^1+'3. Projections'!D14/(1+0.08)^2+'3. Projections'!E14/(1+0.08)^3+'3. Projections'!F14/(1+0.08)^4+'3. Projections'!G14/(1+0.08)^5+'3. Projections'!G14*(1+0.02)/(0.08-0.02)/(1+0.08)^5-'1. Assumptions'!C32)/'1. Assumptions'!C31) -> 38.360926 | C4: =IF((0.08-0.025)<=0,"N/A",('3. Projections'!C14/(1+0.08)^1+'3. Projections'!D14/(1+0.08)^2+'3. Projections'!E14/(1+0.08)^3+'3. Projections'!F14/(1+0.08)^4+'3. Projections'!G14/(1+0.08)^5+'3. Projections'!G14*(1+0.025)/(0.08-0.025)/(1+0.08)^5-'1. Assumptions'!C32)/'1. Assumptions'!C31) -> 40.794662 | D4: =IF((0.08-0.03)<=0,"N/A",('3. Projections'!C14/(1+0.08)^1+'3. Projections'!D14/(1+0.08)^2+'3. Projections'!E14/(1+0.08)^3+'3. Projections'!F14/(1+0.08)^4+'3. Projections'!G14/(1+0.08)^5+'3. Projections'!G14*(1+0.03)/(0.08-0.03)/(1+0.08)^5-'1. Assumptions'!C32)/'1. Assumptions'!C31) -> 43.715145 | E4: =IF((0.08-0.035)<=0,"N/A",('3. Projections'!C14/(1+0.08)^1+'3. Projections'!D14/(1+0.08)^2+'3. Projections'!E14/(1+0.08)^3+'3. Projections'!F14/(1+0.08)^4+'3. Projections'!G14/(1+0.08)^5+'3. Projections'!G14*(1+0.035)/(0.08-0.035)/(1+0.08)^5-'1. Assumptions'!C32)/'1. Assumptions'!C31) -> 47.284624 | F4: =IF((0.08-0.04)<=0,"N/A",('3. Projections'!C14/(1+0.08)^1+'3. Projections'!D14/(1+0.08)^2+'3. Projections'!E14/(1+0.08)^3+'3. Projections'!F14/(1+0.08)^4+'3. Projections'!G14/(1+0.08)^5+'3. Projections'!G14*(1+0.04)/(0.08-0.04)/(1+0.08)^5-'1. Assumptions'!C32)/'1. Assumptions'!C31) -> 51.746473
A5: 0.09 | B5: =IF((0.09-0.02)<=0,"N/A",('3. Projections'!C14/(1+0.09)^1+'3. Projections'!D14/(1+0.09)^2+'3. Projections'!E14/(1+0.09)^3+'3. Projections'!F14/(1+0.09)^4+'3. Projections'!G14/(1+0.09)^5+'3. Projections'!G14*(1+0.02)/(0.09-0.02)/(1+0.09)^5-'1. Assumptions'!C32)/'1. Assumptions'!C31) -> 33.567524 | C5: =IF((0.09-0.025)<=0,"N/A",('3. Projections'!C14/(1+0.09)^1+'3. Projections'!D14/(1+0.09)^2+'3. Projections'!E14/(1+0.09)^3+'3. Projections'!F14/(1+0.09)^4+'3. Projections'!G14/(1+0.09)^5+'3. Projections'!G14*(1+0.025)/(0.09-0.025)/(1+0.09)^5-'1. Assumptions'!C32)/'1. Assumptions'!C31) -> 35.268762 | D5: =IF((0.09-0.03)<=0,"N/A",('3. Projections'!C14/(1+0.09)^1+'3. Projections'!D14/(1+0.09)^2+'3. Projections'!E14/(1+0.09)^3+'3. Projections'!F14/(1+0.09)^4+'3. Projections'!G14/(1+0.09)^5+'3. Projections'!G14*(1+0.03)/(0.09-0.03)/(1+0.09)^5-'1. Assumptions'!C32)/'1. Assumptions'!C31) -> 37.253539 | E5: =IF((0.09-0.035)<=0,"N/A",('3. Projections'!C14/(1+0.09)^1+'3. Projections'!D14/(1+0.09)^2+'3. Projections'!E14/(1+0.09)^3+'3. Projections'!F14/(1+0.09)^4+'3. Projections'!G14/(1+0.09)^5+'3. Projections'!G14*(1+0.035)/(0.09-0.035)/(1+0.09)^5-'1. Assumptions'!C32)/'1. Assumptions'!C31) -> 39.599185 | F5: =IF((0.09-0.04)<=0,"N/A",('3. Projections'!C14/(1+0.09)^1+'3. Projections'!D14/(1+0.09)^2+'3. Projections'!E14/(1+0.09)^3+'3. Projections'!F14/(1+0.09)^4+'3. Projections'!G14/(1+0.09)^5+'3. Projections'!G14*(1+0.04)/(0.09-0.04)/(1+0.09)^5-'1. Assumptions'!C32)/'1. Assumptions'!C31) -> 42.41396
A6: 0.1 | B6: =IF((0.1-0.02)<=0,"N/A",('3. Projections'!C14/(1+0.1)^1+'3. Projections'!D14/(1+0.1)^2+'3. Projections'!E14/(1+0.1)^3+'3. Projections'!F14/(1+0.1)^4+'3. Projections'!G14/(1+0.1)^5+'3. Projections'!G14*(1+0.02)/(0.1-0.02)/(1+0.1)^5-'1. Assumptions'!C32)/'1. Assumptions'!C31) -> 29.975432 | C6: =IF((0.1-0.025)<=0,"N/A",('3. Projections'!C14/(1+0.1)^1+'3. Projections'!D14/(1+0.1)^2+'3. Projections'!E14/(1+0.1)^3+'3. Projections'!F14/(1+0.1)^4+'3. Projections'!G14/(1+0.1)^5+'3. Projections'!G14*(1+0.025)/(0.1-0.025)/(1+0.1)^5-'1. Assumptions'!C32)/'1. Assumptions'!C31) -> 31.21926 | D6: =IF((0.1-0.03)<=0,"N/A",('3. Projections'!C14/(1+0.1)^1+'3. Projections'!D14/(1+0.1)^2+'3. Projections'!E14/(1+0.1)^3+'3. Projections'!F14/(1+0.1)^4+'3. Projections'!G14/(1+0.1)^5+'3. Projections'!G14*(1+0.03)/(0.1-0.03)/(1+0.1)^5-'1. Assumptions'!C32)/'1. Assumptions'!C31) -> 32.640778 | E6: =IF((0.1-0.035)<=0,"N/A",('3. Projections'!C14/(1+0.1)^1+'3. Projections'!D14/(1+0.1)^2+'3. Projections'!E14/(1+0.1)^3+'3. Projections'!F14/(1+0.1)^4+'3. Projections'!G14/(1+0.1)^5+'3. Projections'!G14*(1+0.035)/(0.1-0.035)/(1+0.1)^5-'1. Assumptions'!C32)/'1. Assumptions'!C31) -> 34.280991 | F6: =IF((0.1-0.04)<=0,"N/A",('3. Projections'!C14/(1+0.1)^1+'3. Projections'!D14/(1+0.1)^2+'3. Projections'!E14/(1+0.1)^3+'3. Projections'!F14/(1+0.1)^4+'3. Projections'!G14/(1+0.1)^5+'3. Projections'!G14*(1+0.04)/(0.1-0.04)/(1+0.1)^5-'1. Assumptions'!C32)/'1. Assumptions'!C31) -> 36.194572
A7: 0.11 | B7: =IF((0.11-0.02)<=0,"N/A",('3. Projections'!C14/(1+0.11)^1+'3. Projections'!D14/(1+0.11)^2+'3. Projections'!E14/(1+0.11)^3+'3. Projections'!F14/(1+0.11)^4+'3. Projections'!G14/(1+0.11)^5+'3. Projections'!G14*(1+0.02)/(0.11-0.02)/(1+0.11)^5-'1. Assumptions'!C32)/'1. Assumptions'!C31) -> 27.184093 | C7: =IF((0.11-0.025)<=0,"N/A",('3. Projections'!C14/(1+0.11)^1+'3. Projections'!D14/(1+0.11)^2+'3. Projections'!E14/(1+0.11)^3+'3. Projections'!F14/(1+0.11)^4+'3. Projections'!G14/(1+0.11)^5+'3. Projections'!G14*(1+0.025)/(0.11-0.025)/(1+0.11)^5-'1. Assumptions'!C32)/'1. Assumptions'!C31) -> 28.124962 | D7: =IF((0.11-0.03)<=0,"N/A",('3. Projections'!C14/(1+0.11)^1+'3. Projections'!D14/(1+0.11)^2+'3. Projections'!E14/(1+0.11)^3+'3. Projections'!F14/(1+0.11)^4+'3. Projections'!G14/(1+0.11)^5+'3. Projections'!G14*(1+0.03)/(0.11-0.03)/(1+0.11)^5-'1. Assumptions'!C32)/'1. Assumptions'!C31) -> 29.183439 | E7: =IF((0.11-0.035)<=0,"N/A",('3. Projections'!C14/(1+0.11)^1+'3. Projections'!D14/(1+0.11)^2+'3. Projections'!E14/(1+0.11)^3+'3. Projections'!F14/(1+0.11)^4+'3. Projections'!G14/(1+0.11)^5+'3. Projections'!G14*(1+0.035)/(0.11-0.035)/(1+0.11)^5-'1. Assumptions'!C32)/'1. Assumptions'!C31) -> 30.383047 | F7: =IF((0.11-0.04)<=0,"N/A",('3. Projections'!C14/(1+0.11)^1+'3. Projections'!D14/(1+0.11)^2+'3. Projections'!E14/(1+0.11)^3+'3. Projections'!F14/(1+0.11)^4+'3. Projections'!G14/(1+0.11)^5+'3. Projections'!G14*(1+0.04)/(0.11-0.04)/(1+0.11)^5-'1. Assumptions'!C32)/'1. Assumptions'!C31) -> 31.754027
A8: 0.12 | B8: =IF((0.12-0.02)<=0,"N/A",('3. Projections'!C14/(1+0.12)^1+'3. Projections'!D14/(1+0.12)^2+'3. Projections'!E14/(1+0.12)^3+'3. Projections'!F14/(1+0.12)^4+'3. Projections'!G14/(1+0.12)^5+'3. Projections'!G14*(1+0.02)/(0.12-0.02)/(1+0.12)^5-'1. Assumptions'!C32)/'1. Assumptions'!C31) -> 24.953181 | C8: =IF((0.12-0.025)<=0,"N/A",('3. Projections'!C14/(1+0.12)^1+'3. Projections'!D14/(1+0.12)^2+'3. Projections'!E14/(1+0.12)^3+'3. Projections'!F14/(1+0.12)^4+'3. Projections'!G14/(1+0.12)^5+'3. Projections'!G14*(1+0.025)/(0.12-0.025)/(1+0.12)^5-'1. Assumptions'!C32)/'1. Assumptions'!C31) -> 25.684129 | D8: =IF((0.12-0.03)<=0,"N/A",('3. Projections'!C14/(1+0.12)^1+'3. Projections'!D14/(1+0.12)^2+'3. Projections'!E14/(1+0.12)^3+'3. Projections'!F14/(1+0.12)^4+'3. Projections'!G14/(1+0.12)^5+'3. Projections'!G14*(1+0.03)/(0.12-0.03)/(1+0.12)^5-'1. Assumptions'!C32)/'1. Assumptions'!C31) -> 26.496294 | E8: =IF((0.12-0.035)<=0,"N/A",('3. Projections'!C14/(1+0.12)^1+'3. Projections'!D14/(1+0.12)^2+'3. Projections'!E14/(1+0.12)^3+'3. Projections'!F14/(1+0.12)^4+'3. Projections'!G14/(1+0.12)^5+'3. Projections'!G14*(1+0.035)/(0.12-0.035)/(1+0.12)^5-'1. Assumptions'!C32)/'1. Assumptions'!C31) -> 27.404008 | F8: =IF((0.12-0.04)<=0,"N/A",('3. Projections'!C14/(1+0.12)^1+'3. Projections'!D14/(1+0.12)^2+'3. Projections'!E14/(1+0.12)^3+'3. Projections'!F14/(1+0.12)^4+'3. Projections'!G14/(1+0.12)^5+'3. Projections'!G14*(1+0.04)/(0.12-0.04)/(1+0.12)^5-'1. Assumptions'!C32)/'1. Assumptions'!C31) -> 28.425186
